kcliutils/__init__.py
kcliutils/__main__.py
kcliutils/utils/__init__.py
kcliutils/utils/comment_chars.py
kcliutils/utils/config.py
kcliutils/utils/constants.py
kcliutils/utils/file_creators.py
kcliutils/utils/flows.py
kcliutils/utils/prompt.py
kcliutils/utils/utils.py
kcliutils/utils/texts/__init__.py
kcliutils/utils/texts/all_file_consts.py
kcliutils/utils/texts/api.py
kcliutils/utils/texts/class_.py
kcliutils/utils/texts/enum_.py
kcliutils/utils/texts/file.py
kcliutils/utils/texts/file_consts.py
kcliutils/utils/texts/file_key.py
kcliutils/utils/texts/file_value.py
kcliutils/utils/texts/flow.py
kcliutils/utils/texts/install_dependencies.py
kcliutils/utils/texts/json_class.py
kcliutils/utils/texts/license.py
kcliutils/utils/texts/readme.py
kcliutils/utils/texts/requirements.py
kcliutils/utils/texts/setup.py
kcliutils/utils/texts/utils.py
kcliutils/utils/texts/core_texts/__init__.py
kcliutils/utils/texts/core_texts/api.py
kcliutils/utils/texts/core_texts/class_.py
kcliutils/utils/texts/core_texts/enum_.py
kcliutils/utils/texts/core_texts/file.py
kcliutils/utils/texts/core_texts/file_value.py
kcliutils/utils/texts/core_texts/flow.py
kcliutils/utils/texts/core_texts/gitignore.py
kcliutils/utils/texts/core_texts/install_dependencies.py
kcliutils/utils/texts/core_texts/json_class.py
kcliutils/utils/texts/core_texts/license.py
kcliutils/utils/texts/core_texts/readme.py
kcliutils/utils/texts/core_texts/setup.py
kcliutils-0.1.12.dist-info/LICENSE
kcliutils-0.1.12.dist-info/METADATA
kcliutils-0.1.12.dist-info/WHEEL
kcliutils-0.1.12.dist-info/entry_points.txt
kcliutils-0.1.12.dist-info/top_level.txt
kcliutils-0.1.12.dist-info/RECORD
