Metadata-Version: 2.1
Name: kcliutils
Version: 0.1.12
Summary: kcliutils
Home-page: https://github.com/kkristof200/py_cli_utils
Author: Kristof
License: UNKNOWN
Platform: UNKNOWN
Classifier: Programming Language :: Python :: 3.4
Classifier: Programming Language :: Python :: 3.5
Classifier: Programming Language :: Python :: 3.6
Classifier: Programming Language :: Python :: 3.7
Classifier: Programming Language :: Python :: 3.8
Classifier: Programming Language :: Python :: 3.9
Classifier: License :: OSI Approved :: MIT License
Classifier: Operating System :: OS Independent
Requires-Python: >=3.4
License-File: LICENSE
Requires-Dist: bullet (>=2.2.0)
Requires-Dist: jsoncodable (>=0.1.7)
Requires-Dist: kcu (>=0.0.68)
Requires-Dist: kdependencies (>=0.0.4)
